pipedi/__init__.py
pipedi/pipy.py
pipedi/util/text.py
pipedi-0.0.2.dist-info/METADATA
pipedi-0.0.2.dist-info/WHEEL
pipedi-0.0.2.dist-info/licenses/LICENCE
pipedi-0.0.2.dist-info/RECORD
