Metadata-Version: 2.1
Name: pipedi
Version: 0.0.2
Summary: Enables piping iterables to functions with the pipe character
Project-URL: Homepage, https://github.com/akupar/pipy
Project-URL: Bug Tracker, https://github.com/akupar/pipy/issues
Author-email: Antti Kuparinen <teknovelho@gmail.com>
License-File: LICENCE
Classifier: Development Status :: 3 - Alpha
Classifier: License :: OSI Approved :: MIT License
Classifier: Operating System :: OS Independent
Classifier: Programming Language :: Python :: 3
Classifier: Topic :: Text Processing
Requires-Python: >=3.7
